oc_checksums_worker/__init__.py
oc_checksums_worker/__main__.py
oc_checksums_worker/checksums_worker.py
oc_checksums_worker-2.1.0.dist-info/licenses/LICENSE
oc_checksums_worker-2.1.0.dist-info/METADATA
oc_checksums_worker-2.1.0.dist-info/WHEEL
oc_checksums_worker-2.1.0.dist-info/top_level.txt
oc_checksums_worker-2.1.0.dist-info/RECORD
