Metadata-Version: 2.4
Name: oc-checksums-worker
Version: 2.1.0
Summary: Checksums worker for AMQP queue
License: Apache2.0
Requires-Python: >=3.6
License-File: LICENSE
Requires-Dist: oc-checksumsq
Requires-Dist: oc-delivery-apps>=11.2.9
Requires-Dist: oc-orm-initializator
Requires-Dist: oc-cdtapi
Requires-Dist: oc_logging
Dynamic: description
Dynamic: description-content-type
Dynamic: license
Dynamic: license-file
Dynamic: requires-dist
Dynamic: requires-python
Dynamic: summary
